iperf3/__init__.py
iperf3/iperf3.py
iperf3-0.1.10.dist-info/DESCRIPTION.rst
iperf3-0.1.10.dist-info/METADATA
iperf3-0.1.10.dist-info/RECORD
iperf3-0.1.10.dist-info/WHEEL
iperf3-0.1.10.dist-info/metadata.json
iperf3-0.1.10.dist-info/top_level.txt
